{
    "yes": [
        {
            "idx": 1,
            "output": "not visible"
        },
        {
            "idx": 3,
            "output": "not visible"
        },
        {
            "idx": 4,
            "output": "not visible"
        },
        {
            "idx": 5,
            "output": "not visible"
        },
        {
            "idx": 6,
            "output": "not visible"
        },
        {
            "idx": 7,
            "output": "not visible"
        },
        {
            "idx": 9,
            "output": "not visible"
        },
        {
            "idx": 10,
            "output": "visible"
        },
        {
            "idx": 11,
            "output": "not visible"
        },
        {
            "idx": 14,
            "output": "not visible"
        },
        {
            "idx": 17,
            "output": "not visible"
        },
        {
            "idx": 18,
            "output": "not visible"
        },
        {
            "idx": 19,
            "output": "not visible"
        },
        {
            "idx": 21,
            "output": "not visible"
        },
        {
            "idx": 22,
            "output": "not visible"
        },
        {
            "idx": 24,
            "output": "not visible"
        },
        {
            "idx": 25,
            "output": "not visible"
        },
        {
            "idx": 26,
            "output": "visible"
        },
        {
            "idx": 27,
            "output": "not visible"
        },
        {
            "idx": 28,
            "output": "not visible"
        },
        {
            "idx": 30,
            "output": "not visible"
        },
        {
            "idx": 31,
            "output": "not visible"
        },
        {
            "idx": 34,
            "output": "not visible"
        },
        {
            "idx": 35,
            "output": "not visible"
        },
        {
            "idx": 37,
            "output": "not visible"
        },
        {
            "idx": 38,
            "output": "not visible"
        },
        {
            "idx": 39,
            "output": "not visible"
        },
        {
            "idx": 42,
            "output": "not visible"
        },
        {
            "idx": 43,
            "output": "not visible"
        },
        {
            "idx": 44,
            "output": "not visible"
        },
        {
            "idx": 46,
            "output": "not visible"
        },
        {
            "idx": 48,
            "output": "not visible"
        },
        {
            "idx": 49,
            "output": "not visible"
        },
        {
            "idx": 50,
            "output": "not visible"
        },
        {
            "idx": 51,
            "output": "not visible"
        },
        {
            "idx": 52,
            "output": "not visible"
        },
        {
            "idx": 53,
            "output": "not visible"
        },
        {
            "idx": 54,
            "output": "not visible"
        },
        {
            "idx": 55,
            "output": "not visible"
        },
        {
            "idx": 56,
            "output": "not visible"
        },
        {
            "idx": 57,
            "output": "not visible"
        },
        {
            "idx": 58,
            "output": "not visible"
        },
        {
            "idx": 59,
            "output": "not visible"
        },
        {
            "idx": 60,
            "output": "not visible"
        },
        {
            "idx": 61,
            "output": "not visible"
        },
        {
            "idx": 62,
            "output": "not visible"
        },
        {
            "idx": 63,
            "output": "not visible"
        },
        {
            "idx": 64,
            "output": "not visible"
        },
        {
            "idx": 66,
            "output": "not visible"
        },
        {
            "idx": 67,
            "output": "not visible"
        },
        {
            "idx": 68,
            "output": "not visible"
        },
        {
            "idx": 69,
            "output": "not visible"
        },
        {
            "idx": 78,
            "output": "visible"
        },
        {
            "idx": 81,
            "output": "not visible"
        },
        {
            "idx": 84,
            "output": "not visible"
        },
        {
            "idx": 85,
            "output": "not visible"
        },
        {
            "idx": 86,
            "output": "not visible"
        },
        {
            "idx": 87,
            "output": "not visible"
        },
        {
            "idx": 91,
            "output": "not visible"
        },
        {
            "idx": 92,
            "output": "not visible"
        },
        {
            "idx": 95,
            "output": "not visible"
        },
        {
            "idx": 96,
            "output": "not visible"
        },
        {
            "idx": 98,
            "output": "visible"
        },
        {
            "idx": 101,
            "output": "not visible"
        },
        {
            "idx": 102,
            "output": "not visible"
        },
        {
            "idx": 106,
            "output": "not visible"
        },
        {
            "idx": 110,
            "output": "not visible"
        },
        {
            "idx": 111,
            "output": "not visible"
        },
        {
            "idx": 114,
            "output": "not visible"
        },
        {
            "idx": 115,
            "output": "not visible"
        },
        {
            "idx": 119,
            "output": "not visible"
        },
        {
            "idx": 124,
            "output": "not visible"
        },
        {
            "idx": 125,
            "output": "not visible"
        },
        {
            "idx": 129,
            "output": "not visible"
        },
        {
            "idx": 130,
            "output": "not visible"
        },
        {
            "idx": 131,
            "output": "not visible"
        },
        {
            "idx": 134,
            "output": "not visible"
        },
        {
            "idx": 135,
            "output": "not visible"
        },
        {
            "idx": 136,
            "output": "visible"
        },
        {
            "idx": 137,
            "output": "not visible"
        },
        {
            "idx": 139,
            "output": "not visible"
        },
        {
            "idx": 140,
            "output": "not visible"
        },
        {
            "idx": 141,
            "output": "not visible"
        },
        {
            "idx": 150,
            "output": "not visible"
        },
        {
            "idx": 152,
            "output": "not visible"
        },
        {
            "idx": 156,
            "output": "not visible"
        },
        {
            "idx": 157,
            "output": "not visible"
        },
        {
            "idx": 158,
            "output": "not visible"
        },
        {
            "idx": 162,
            "output": "not visible"
        },
        {
            "idx": 164,
            "output": "not visible"
        },
        {
            "idx": 166,
            "output": "not visible"
        },
        {
            "idx": 167,
            "output": "not visible"
        },
        {
            "idx": 170,
            "output": "visible"
        },
        {
            "idx": 171,
            "output": "visible"
        },
        {
            "idx": 174,
            "output": "not visible"
        },
        {
            "idx": 176,
            "output": "not visible"
        },
        {
            "idx": 179,
            "output": "not visible"
        },
        {
            "idx": 180,
            "output": "not visible"
        },
        {
            "idx": 183,
            "output": "not visible"
        },
        {
            "idx": 185,
            "output": "not visible"
        },
        {
            "idx": 186,
            "output": "not visible"
        },
        {
            "idx": 187,
            "output": "not visible"
        },
        {
            "idx": 190,
            "output": "not visible"
        },
        {
            "idx": 192,
            "output": "not visible"
        },
        {
            "idx": 193,
            "output": "not visible"
        },
        {
            "idx": 196,
            "output": "not visible"
        },
        {
            "idx": 198,
            "output": "not visible"
        },
        {
            "idx": 199,
            "output": "not visible"
        },
        {
            "idx": 204,
            "output": "not visible"
        },
        {
            "idx": 205,
            "output": "not visible"
        },
        {
            "idx": 207,
            "output": "not visible"
        },
        {
            "idx": 209,
            "output": "not visible"
        },
        {
            "idx": 210,
            "output": "not visible"
        },
        {
            "idx": 211,
            "output": "not visible"
        },
        {
            "idx": 212,
            "output": "not visible"
        },
        {
            "idx": 215,
            "output": "not visible"
        },
        {
            "idx": 216,
            "output": "not visible"
        },
        {
            "idx": 217,
            "output": "not visible"
        },
        {
            "idx": 218,
            "output": "not visible"
        },
        {
            "idx": 220,
            "output": "not visible"
        },
        {
            "idx": 222,
            "output": "not visible"
        },
        {
            "idx": 223,
            "output": "not visible"
        },
        {
            "idx": 226,
            "output": "not visible"
        },
        {
            "idx": 227,
            "output": "not visible"
        },
        {
            "idx": 228,
            "output": "not visible"
        },
        {
            "idx": 230,
            "output": "not visible"
        },
        {
            "idx": 231,
            "output": "not visible"
        },
        {
            "idx": 232,
            "output": "visible"
        },
        {
            "idx": 233,
            "output": "not visible"
        },
        {
            "idx": 247,
            "output": "not visible"
        },
        {
            "idx": 252,
            "output": "not visible"
        },
        {
            "idx": 258,
            "output": "visible"
        },
        {
            "idx": 262,
            "output": "visible"
        },
        {
            "idx": 263,
            "output": "not visible"
        },
        {
            "idx": 266,
            "output": "not visible"
        },
        {
            "idx": 273,
            "output": "not visible"
        },
        {
            "idx": 276,
            "output": "not visible"
        },
        {
            "idx": 277,
            "output": "not visible"
        },
        {
            "idx": 278,
            "output": "not visible"
        },
        {
            "idx": 280,
            "output": "not visible"
        },
        {
            "idx": 281,
            "output": "visible"
        },
        {
            "idx": 284,
            "output": "not visible"
        },
        {
            "idx": 285,
            "output": "visible"
        },
        {
            "idx": 286,
            "output": "not visible"
        },
        {
            "idx": 288,
            "output": "not visible"
        },
        {
            "idx": 289,
            "output": "not visible"
        },
        {
            "idx": 291,
            "output": "not visible"
        },
        {
            "idx": 292,
            "output": "not visible"
        },
        {
            "idx": 293,
            "output": "visible"
        },
        {
            "idx": 297,
            "output": "not visible"
        },
        {
            "idx": 298,
            "output": "not visible"
        },
        {
            "idx": 299,
            "output": "not visible"
        },
        {
            "idx": 300,
            "output": "not visible"
        },
        {
            "idx": 301,
            "output": "visible"
        },
        {
            "idx": 302,
            "output": "not visible"
        },
        {
            "idx": 305,
            "output": "visible"
        },
        {
            "idx": 307,
            "output": "not visible"
        },
        {
            "idx": 309,
            "output": "visible"
        },
        {
            "idx": 310,
            "output": "not visible"
        },
        {
            "idx": 311,
            "output": "visible"
        },
        {
            "idx": 312,
            "output": "visible"
        },
        {
            "idx": 313,
            "output": "not visible"
        },
        {
            "idx": 315,
            "output": "not visible"
        },
        {
            "idx": 316,
            "output": "not visible"
        },
        {
            "idx": 317,
            "output": "not visible"
        },
        {
            "idx": 318,
            "output": "not visible"
        },
        {
            "idx": 319,
            "output": "not visible"
        },
        {
            "idx": 320,
            "output": "not visible"
        },
        {
            "idx": 321,
            "output": "not visible"
        },
        {
            "idx": 322,
            "output": "not visible"
        },
        {
            "idx": 324,
            "output": "visible"
        },
        {
            "idx": 325,
            "output": "not visible"
        },
        {
            "idx": 326,
            "output": "not visible"
        },
        {
            "idx": 328,
            "output": "visible"
        },
        {
            "idx": 329,
            "output": "not visible"
        },
        {
            "idx": 331,
            "output": "not visible"
        },
        {
            "idx": 332,
            "output": "not visible"
        },
        {
            "idx": 333,
            "output": "not visible"
        },
        {
            "idx": 335,
            "output": "visible"
        },
        {
            "idx": 336,
            "output": "not visible"
        },
        {
            "idx": 337,
            "output": "not visible"
        },
        {
            "idx": 339,
            "output": "not visible"
        },
        {
            "idx": 340,
            "output": "not visible"
        },
        {
            "idx": 342,
            "output": "not visible"
        },
        {
            "idx": 344,
            "output": "not visible"
        },
        {
            "idx": 346,
            "output": "not visible"
        },
        {
            "idx": 348,
            "output": "not visible"
        },
        {
            "idx": 349,
            "output": "not visible"
        },
        {
            "idx": 350,
            "output": "not visible"
        },
        {
            "idx": 351,
            "output": "not visible"
        },
        {
            "idx": 352,
            "output": "not visible"
        },
        {
            "idx": 355,
            "output": "not visible"
        },
        {
            "idx": 359,
            "output": "not visible"
        },
        {
            "idx": 360,
            "output": "not visible"
        },
        {
            "idx": 361,
            "output": "not visible"
        },
        {
            "idx": 363,
            "output": "not visible"
        },
        {
            "idx": 365,
            "output": "not visible"
        },
        {
            "idx": 367,
            "output": "not visible"
        },
        {
            "idx": 368,
            "output": "not visible"
        },
        {
            "idx": 371,
            "output": "not visible"
        },
        {
            "idx": 372,
            "output": "not visible"
        },
        {
            "idx": 373,
            "output": "not visible"
        },
        {
            "idx": 374,
            "output": "not visible"
        },
        {
            "idx": 375,
            "output": "not visible"
        },
        {
            "idx": 376,
            "output": "not visible"
        },
        {
            "idx": 378,
            "output": "not visible"
        },
        {
            "idx": 380,
            "output": "visible"
        },
        {
            "idx": 381,
            "output": "not visible"
        },
        {
            "idx": 382,
            "output": "not visible"
        },
        {
            "idx": 383,
            "output": "not visible"
        },
        {
            "idx": 384,
            "output": "not visible"
        },
        {
            "idx": 385,
            "output": "not visible"
        },
        {
            "idx": 386,
            "output": "not visible"
        },
        {
            "idx": 387,
            "output": "not visible"
        },
        {
            "idx": 388,
            "output": "not visible"
        },
        {
            "idx": 389,
            "output": "visible"
        },
        {
            "idx": 390,
            "output": "not visible"
        },
        {
            "idx": 391,
            "output": "not visible"
        },
        {
            "idx": 392,
            "output": "not visible"
        },
        {
            "idx": 393,
            "output": "not visible"
        },
        {
            "idx": 394,
            "output": "not visible"
        },
        {
            "idx": 395,
            "output": "not visible"
        },
        {
            "idx": 397,
            "output": "not visible"
        },
        {
            "idx": 399,
            "output": "not visible"
        },
        {
            "idx": 400,
            "output": "not visible"
        },
        {
            "idx": 401,
            "output": "not visible"
        },
        {
            "idx": 402,
            "output": "not visible"
        },
        {
            "idx": 403,
            "output": "visible"
        },
        {
            "idx": 404,
            "output": "not visible"
        },
        {
            "idx": 405,
            "output": "not visible"
        },
        {
            "idx": 407,
            "output": "not visible"
        },
        {
            "idx": 408,
            "output": "not visible"
        },
        {
            "idx": 410,
            "output": "not visible"
        },
        {
            "idx": 411,
            "output": "not visible"
        },
        {
            "idx": 412,
            "output": "not visible"
        },
        {
            "idx": 413,
            "output": "not visible"
        },
        {
            "idx": 415,
            "output": "not visible"
        },
        {
            "idx": 416,
            "output": "not visible"
        },
        {
            "idx": 417,
            "output": "not visible"
        },
        {
            "idx": 418,
            "output": "not visible"
        },
        {
            "idx": 419,
            "output": "not visible"
        },
        {
            "idx": 422,
            "output": "not visible"
        },
        {
            "idx": 424,
            "output": "not visible"
        },
        {
            "idx": 427,
            "output": "not visible"
        },
        {
            "idx": 428,
            "output": "visible"
        },
        {
            "idx": 429,
            "output": "not visible"
        },
        {
            "idx": 430,
            "output": "not visible"
        },
        {
            "idx": 431,
            "output": "not visible"
        },
        {
            "idx": 433,
            "output": "not visible"
        },
        {
            "idx": 434,
            "output": "not visible"
        },
        {
            "idx": 435,
            "output": "not visible"
        },
        {
            "idx": 436,
            "output": "not visible"
        },
        {
            "idx": 438,
            "output": "not visible"
        },
        {
            "idx": 440,
            "output": "visible"
        },
        {
            "idx": 442,
            "output": "visible"
        },
        {
            "idx": 443,
            "output": "not visible"
        },
        {
            "idx": 446,
            "output": "not visible"
        },
        {
            "idx": 447,
            "output": "visible"
        },
        {
            "idx": 448,
            "output": "not visible"
        },
        {
            "idx": 449,
            "output": "not visible"
        },
        {
            "idx": 451,
            "output": "not visible"
        },
        {
            "idx": 452,
            "output": "not visible"
        },
        {
            "idx": 453,
            "output": "not visible"
        },
        {
            "idx": 454,
            "output": "not visible"
        },
        {
            "idx": 455,
            "output": "not visible"
        },
        {
            "idx": 456,
            "output": "not visible"
        },
        {
            "idx": 458,
            "output": "not visible"
        },
        {
            "idx": 459,
            "output": "not visible"
        },
        {
            "idx": 460,
            "output": "not visible"
        },
        {
            "idx": 461,
            "output": "not visible"
        },
        {
            "idx": 462,
            "output": "not visible"
        },
        {
            "idx": 463,
            "output": "not visible"
        },
        {
            "idx": 464,
            "output": "not visible"
        },
        {
            "idx": 465,
            "output": "not visible"
        },
        {
            "idx": 466,
            "output": "not visible"
        },
        {
            "idx": 468,
            "output": "not visible"
        },
        {
            "idx": 470,
            "output": "not visible"
        },
        {
            "idx": 472,
            "output": "not visible"
        },
        {
            "idx": 473,
            "output": "not visible"
        },
        {
            "idx": 474,
            "output": "not visible"
        },
        {
            "idx": 477,
            "output": "visible"
        },
        {
            "idx": 478,
            "output": "not visible"
        },
        {
            "idx": 479,
            "output": "not visible"
        },
        {
            "idx": 483,
            "output": "not visible"
        },
        {
            "idx": 484,
            "output": "not visible"
        },
        {
            "idx": 485,
            "output": "not visible"
        },
        {
            "idx": 486,
            "output": "not visible"
        },
        {
            "idx": 487,
            "output": "not visible"
        },
        {
            "idx": 488,
            "output": "not visible"
        },
        {
            "idx": 489,
            "output": "not visible"
        },
        {
            "idx": 490,
            "output": "not visible"
        },
        {
            "idx": 495,
            "output": "not visible"
        },
        {
            "idx": 497,
            "output": "not visible"
        },
        {
            "idx": 498,
            "output": "not visible"
        },
        {
            "idx": 500,
            "output": "not visible"
        },
        {
            "idx": 501,
            "output": "not visible"
        },
        {
            "idx": 504,
            "output": "not visible"
        },
        {
            "idx": 505,
            "output": "visible"
        },
        {
            "idx": 508,
            "output": "not visible"
        },
        {
            "idx": 509,
            "output": "not visible"
        },
        {
            "idx": 510,
            "output": "not visible"
        },
        {
            "idx": 511,
            "output": "not visible"
        },
        {
            "idx": 512,
            "output": "not visible"
        },
        {
            "idx": 513,
            "output": "not visible"
        },
        {
            "idx": 515,
            "output": "not visible"
        },
        {
            "idx": 518,
            "output": "not visible"
        },
        {
            "idx": 519,
            "output": "not visible"
        },
        {
            "idx": 520,
            "output": "not visible"
        },
        {
            "idx": 521,
            "output": "not visible"
        },
        {
            "idx": 522,
            "output": "not visible"
        },
        {
            "idx": 523,
            "output": "not visible"
        },
        {
            "idx": 524,
            "output": "not visible"
        },
        {
            "idx": 525,
            "output": "not visible"
        },
        {
            "idx": 527,
            "output": "not visible"
        },
        {
            "idx": 528,
            "output": "not visible"
        },
        {
            "idx": 529,
            "output": "not visible"
        },
        {
            "idx": 530,
            "output": "not visible"
        },
        {
            "idx": 531,
            "output": "not visible"
        },
        {
            "idx": 532,
            "output": "visible"
        },
        {
            "idx": 533,
            "output": "not visible"
        },
        {
            "idx": 534,
            "output": "not visible"
        },
        {
            "idx": 535,
            "output": "not visible"
        },
        {
            "idx": 537,
            "output": "not visible"
        },
        {
            "idx": 539,
            "output": "not visible"
        },
        {
            "idx": 540,
            "output": "not visible"
        },
        {
            "idx": 541,
            "output": "not visible"
        },
        {
            "idx": 542,
            "output": "not visible"
        },
        {
            "idx": 543,
            "output": "not visible"
        },
        {
            "idx": 544,
            "output": "not visible"
        },
        {
            "idx": 546,
            "output": "not visible"
        },
        {
            "idx": 548,
            "output": "not visible"
        },
        {
            "idx": 549,
            "output": "not visible"
        },
        {
            "idx": 550,
            "output": "not visible"
        },
        {
            "idx": 551,
            "output": "not visible"
        },
        {
            "idx": 552,
            "output": "not visible"
        },
        {
            "idx": 553,
            "output": "not visible"
        },
        {
            "idx": 555,
            "output": "not visible"
        },
        {
            "idx": 556,
            "output": "not visible"
        },
        {
            "idx": 557,
            "output": "visible"
        },
        {
            "idx": 559,
            "output": "not visible"
        },
        {
            "idx": 561,
            "output": "not visible"
        },
        {
            "idx": 562,
            "output": "not visible"
        },
        {
            "idx": 563,
            "output": "not visible"
        },
        {
            "idx": 564,
            "output": "not visible"
        },
        {
            "idx": 565,
            "output": "not visible"
        },
        {
            "idx": 566,
            "output": "not visible"
        },
        {
            "idx": 567,
            "output": "not visible"
        },
        {
            "idx": 568,
            "output": "visible"
        },
        {
            "idx": 570,
            "output": "not visible"
        },
        {
            "idx": 571,
            "output": "not visible"
        },
        {
            "idx": 573,
            "output": "not visible"
        },
        {
            "idx": 574,
            "output": "not visible"
        },
        {
            "idx": 575,
            "output": "not visible"
        },
        {
            "idx": 577,
            "output": "not visible"
        },
        {
            "idx": 578,
            "output": "not visible"
        },
        {
            "idx": 582,
            "output": "not visible"
        },
        {
            "idx": 584,
            "output": "not visible"
        },
        {
            "idx": 585,
            "output": "not visible"
        },
        {
            "idx": 587,
            "output": "not visible"
        },
        {
            "idx": 589,
            "output": "not visible"
        },
        {
            "idx": 591,
            "output": "not visible"
        },
        {
            "idx": 592,
            "output": "visible"
        },
        {
            "idx": 593,
            "output": "not visible"
        },
        {
            "idx": 597,
            "output": "not visible"
        },
        {
            "idx": 598,
            "output": "not visible"
        },
        {
            "idx": 600,
            "output": "visible"
        },
        {
            "idx": 602,
            "output": "not visible"
        },
        {
            "idx": 603,
            "output": "not visible"
        },
        {
            "idx": 604,
            "output": "not visible"
        },
        {
            "idx": 605,
            "output": "not visible"
        },
        {
            "idx": 606,
            "output": "not visible"
        },
        {
            "idx": 608,
            "output": "not visible"
        },
        {
            "idx": 609,
            "output": "not visible"
        },
        {
            "idx": 610,
            "output": "not visible"
        },
        {
            "idx": 611,
            "output": "not visible"
        },
        {
            "idx": 612,
            "output": "not visible"
        },
        {
            "idx": 613,
            "output": "not visible"
        },
        {
            "idx": 615,
            "output": "not visible"
        },
        {
            "idx": 616,
            "output": "not visible"
        },
        {
            "idx": 617,
            "output": "not visible"
        },
        {
            "idx": 618,
            "output": "visible"
        },
        {
            "idx": 619,
            "output": "not visible"
        },
        {
            "idx": 622,
            "output": "not visible"
        },
        {
            "idx": 623,
            "output": "not visible"
        },
        {
            "idx": 624,
            "output": "not visible"
        },
        {
            "idx": 625,
            "output": "not visible"
        },
        {
            "idx": 626,
            "output": "visible"
        },
        {
            "idx": 627,
            "output": "not visible"
        },
        {
            "idx": 630,
            "output": "not visible"
        },
        {
            "idx": 631,
            "output": "not visible"
        },
        {
            "idx": 632,
            "output": "not visible"
        },
        {
            "idx": 633,
            "output": "not visible"
        },
        {
            "idx": 635,
            "output": "not visible"
        },
        {
            "idx": 636,
            "output": "not visible"
        },
        {
            "idx": 637,
            "output": "not visible"
        },
        {
            "idx": 641,
            "output": "visible"
        },
        {
            "idx": 642,
            "output": "not visible"
        },
        {
            "idx": 647,
            "output": "not visible"
        },
        {
            "idx": 652,
            "output": "not visible"
        },
        {
            "idx": 653,
            "output": "visible"
        },
        {
            "idx": 656,
            "output": "not visible"
        },
        {
            "idx": 658,
            "output": "not visible"
        },
        {
            "idx": 661,
            "output": "not visible"
        },
        {
            "idx": 663,
            "output": "not visible"
        },
        {
            "idx": 664,
            "output": "not visible"
        },
        {
            "idx": 666,
            "output": "not visible"
        },
        {
            "idx": 667,
            "output": "not visible"
        },
        {
            "idx": 668,
            "output": "not visible"
        },
        {
            "idx": 670,
            "output": "not visible"
        },
        {
            "idx": 671,
            "output": "not visible"
        },
        {
            "idx": 672,
            "output": "not visible"
        },
        {
            "idx": 674,
            "output": "not visible"
        },
        {
            "idx": 675,
            "output": "not visible"
        },
        {
            "idx": 676,
            "output": "not visible"
        },
        {
            "idx": 677,
            "output": "not visible"
        },
        {
            "idx": 679,
            "output": "visible"
        },
        {
            "idx": 680,
            "output": "not visible"
        },
        {
            "idx": 682,
            "output": "not visible"
        },
        {
            "idx": 683,
            "output": "not visible"
        },
        {
            "idx": 684,
            "output": "not visible"
        },
        {
            "idx": 685,
            "output": "not visible"
        },
        {
            "idx": 686,
            "output": "visible"
        },
        {
            "idx": 687,
            "output": "not visible"
        },
        {
            "idx": 689,
            "output": "not visible"
        },
        {
            "idx": 690,
            "output": "visible"
        },
        {
            "idx": 691,
            "output": "not visible"
        },
        {
            "idx": 693,
            "output": "not visible"
        },
        {
            "idx": 694,
            "output": "not visible"
        },
        {
            "idx": 695,
            "output": "not visible"
        },
        {
            "idx": 696,
            "output": "not visible"
        },
        {
            "idx": 698,
            "output": "not visible"
        },
        {
            "idx": 702,
            "output": "not visible"
        },
        {
            "idx": 703,
            "output": "not visible"
        },
        {
            "idx": 704,
            "output": "visible"
        },
        {
            "idx": 705,
            "output": "not visible"
        },
        {
            "idx": 706,
            "output": "not visible"
        },
        {
            "idx": 707,
            "output": "not visible"
        },
        {
            "idx": 709,
            "output": "not visible"
        },
        {
            "idx": 712,
            "output": "not visible"
        },
        {
            "idx": 714,
            "output": "not visible"
        },
        {
            "idx": 715,
            "output": "not visible"
        },
        {
            "idx": 716,
            "output": "not visible"
        },
        {
            "idx": 717,
            "output": "not visible"
        },
        {
            "idx": 718,
            "output": "not visible"
        },
        {
            "idx": 719,
            "output": "not visible"
        },
        {
            "idx": 720,
            "output": "not visible"
        },
        {
            "idx": 722,
            "output": "not visible"
        },
        {
            "idx": 723,
            "output": "not visible"
        },
        {
            "idx": 725,
            "output": "not visible"
        },
        {
            "idx": 726,
            "output": "not visible"
        },
        {
            "idx": 727,
            "output": "not visible"
        },
        {
            "idx": 729,
            "output": "not visible"
        },
        {
            "idx": 731,
            "output": "not visible"
        },
        {
            "idx": 732,
            "output": "not visible"
        },
        {
            "idx": 733,
            "output": "not visible"
        },
        {
            "idx": 734,
            "output": "not visible"
        },
        {
            "idx": 735,
            "output": "not visible"
        },
        {
            "idx": 737,
            "output": "not visible"
        },
        {
            "idx": 738,
            "output": "not visible"
        },
        {
            "idx": 739,
            "output": "not visible"
        },
        {
            "idx": 740,
            "output": "not visible"
        },
        {
            "idx": 741,
            "output": "not visible"
        },
        {
            "idx": 742,
            "output": "not visible"
        },
        {
            "idx": 745,
            "output": "visible"
        },
        {
            "idx": 746,
            "output": "visible"
        },
        {
            "idx": 747,
            "output": "visible"
        },
        {
            "idx": 748,
            "output": "not visible"
        },
        {
            "idx": 749,
            "output": "not visible"
        },
        {
            "idx": 750,
            "output": "not visible"
        },
        {
            "idx": 751,
            "output": "not visible"
        },
        {
            "idx": 753,
            "output": "not visible"
        },
        {
            "idx": 756,
            "output": "not visible"
        },
        {
            "idx": 757,
            "output": "not visible"
        },
        {
            "idx": 759,
            "output": "not visible"
        },
        {
            "idx": 760,
            "output": "not visible"
        },
        {
            "idx": 764,
            "output": "not visible"
        },
        {
            "idx": 765,
            "output": "not visible"
        },
        {
            "idx": 766,
            "output": "visible"
        },
        {
            "idx": 769,
            "output": "not visible"
        },
        {
            "idx": 770,
            "output": "not visible"
        },
        {
            "idx": 771,
            "output": "not visible"
        },
        {
            "idx": 774,
            "output": "not visible"
        },
        {
            "idx": 775,
            "output": "visible"
        },
        {
            "idx": 776,
            "output": "not visible"
        },
        {
            "idx": 777,
            "output": "not visible"
        },
        {
            "idx": 778,
            "output": "not visible"
        },
        {
            "idx": 780,
            "output": "not visible"
        },
        {
            "idx": 781,
            "output": "not visible"
        },
        {
            "idx": 782,
            "output": "not visible"
        },
        {
            "idx": 785,
            "output": "visible"
        },
        {
            "idx": 786,
            "output": "not visible"
        },
        {
            "idx": 787,
            "output": "not visible"
        },
        {
            "idx": 788,
            "output": "not visible"
        },
        {
            "idx": 790,
            "output": "not visible"
        },
        {
            "idx": 791,
            "output": "not visible"
        },
        {
            "idx": 792,
            "output": "not visible"
        },
        {
            "idx": 793,
            "output": "not visible"
        },
        {
            "idx": 794,
            "output": "visible"
        },
        {
            "idx": 796,
            "output": "not visible"
        },
        {
            "idx": 797,
            "output": "not visible"
        },
        {
            "idx": 798,
            "output": "not visible"
        },
        {
            "idx": 800,
            "output": "not visible"
        },
        {
            "idx": 801,
            "output": "not visible"
        },
        {
            "idx": 802,
            "output": "not visible"
        },
        {
            "idx": 803,
            "output": "not visible"
        },
        {
            "idx": 804,
            "output": "not visible"
        },
        {
            "idx": 806,
            "output": "not visible"
        },
        {
            "idx": 807,
            "output": "not visible"
        },
        {
            "idx": 808,
            "output": "not visible"
        },
        {
            "idx": 809,
            "output": "not visible"
        },
        {
            "idx": 810,
            "output": "visible"
        },
        {
            "idx": 811,
            "output": "not visible"
        },
        {
            "idx": 812,
            "output": "not visible"
        },
        {
            "idx": 813,
            "output": "not visible"
        },
        {
            "idx": 814,
            "output": "not visible"
        },
        {
            "idx": 816,
            "output": "not visible"
        },
        {
            "idx": 817,
            "output": "not visible"
        },
        {
            "idx": 818,
            "output": "not visible"
        },
        {
            "idx": 819,
            "output": "not visible"
        },
        {
            "idx": 820,
            "output": "not visible"
        },
        {
            "idx": 821,
            "output": "not visible"
        },
        {
            "idx": 823,
            "output": "not visible"
        },
        {
            "idx": 824,
            "output": "not visible"
        },
        {
            "idx": 825,
            "output": "not visible"
        },
        {
            "idx": 826,
            "output": "not visible"
        },
        {
            "idx": 827,
            "output": "not visible"
        },
        {
            "idx": 828,
            "output": "not visible"
        },
        {
            "idx": 829,
            "output": "not visible"
        },
        {
            "idx": 830,
            "output": "not visible"
        },
        {
            "idx": 831,
            "output": "not visible"
        },
        {
            "idx": 832,
            "output": "not visible"
        },
        {
            "idx": 835,
            "output": "not visible"
        },
        {
            "idx": 837,
            "output": "not visible"
        },
        {
            "idx": 838,
            "output": "not visible"
        },
        {
            "idx": 839,
            "output": "not visible"
        },
        {
            "idx": 841,
            "output": "not visible"
        },
        {
            "idx": 843,
            "output": "not visible"
        },
        {
            "idx": 844,
            "output": "not visible"
        },
        {
            "idx": 845,
            "output": "not visible"
        },
        {
            "idx": 846,
            "output": "not visible"
        },
        {
            "idx": 847,
            "output": "not visible"
        },
        {
            "idx": 848,
            "output": "not visible"
        },
        {
            "idx": 849,
            "output": "visible"
        },
        {
            "idx": 851,
            "output": "not visible"
        },
        {
            "idx": 854,
            "output": "not visible"
        },
        {
            "idx": 858,
            "output": "not visible"
        },
        {
            "idx": 859,
            "output": "not visible"
        },
        {
            "idx": 860,
            "output": "not visible"
        },
        {
            "idx": 861,
            "output": "not visible"
        },
        {
            "idx": 862,
            "output": "not visible"
        },
        {
            "idx": 863,
            "output": "not visible"
        },
        {
            "idx": 865,
            "output": "not visible"
        },
        {
            "idx": 866,
            "output": "not visible"
        },
        {
            "idx": 867,
            "output": "not visible"
        },
        {
            "idx": 868,
            "output": "not visible"
        },
        {
            "idx": 869,
            "output": "not visible"
        },
        {
            "idx": 871,
            "output": "not visible"
        },
        {
            "idx": 872,
            "output": "not visible"
        },
        {
            "idx": 876,
            "output": "not visible"
        },
        {
            "idx": 879,
            "output": "not visible"
        },
        {
            "idx": 880,
            "output": "not visible"
        },
        {
            "idx": 883,
            "output": "not visible"
        },
        {
            "idx": 886,
            "output": "not visible"
        },
        {
            "idx": 888,
            "output": "not visible"
        },
        {
            "idx": 891,
            "output": "not visible"
        },
        {
            "idx": 892,
            "output": "not visible"
        },
        {
            "idx": 893,
            "output": "not visible"
        },
        {
            "idx": 894,
            "output": "not visible"
        },
        {
            "idx": 896,
            "output": "not visible"
        },
        {
            "idx": 897,
            "output": "not visible"
        },
        {
            "idx": 899,
            "output": "not visible"
        },
        {
            "idx": 900,
            "output": "not visible"
        },
        {
            "idx": 901,
            "output": "not visible"
        },
        {
            "idx": 902,
            "output": "visible"
        },
        {
            "idx": 903,
            "output": "not visible"
        },
        {
            "idx": 904,
            "output": "not visible"
        },
        {
            "idx": 905,
            "output": "not visible"
        },
        {
            "idx": 906,
            "output": "not visible"
        },
        {
            "idx": 907,
            "output": "not visible"
        },
        {
            "idx": 908,
            "output": "not visible"
        },
        {
            "idx": 909,
            "output": "not visible"
        },
        {
            "idx": 910,
            "output": "not visible"
        },
        {
            "idx": 912,
            "output": "not visible"
        },
        {
            "idx": 913,
            "output": "not visible"
        },
        {
            "idx": 915,
            "output": "not visible"
        },
        {
            "idx": 916,
            "output": "not visible"
        },
        {
            "idx": 919,
            "output": "not visible"
        },
        {
            "idx": 920,
            "output": "not visible"
        },
        {
            "idx": 921,
            "output": "not visible"
        },
        {
            "idx": 923,
            "output": "not visible"
        },
        {
            "idx": 924,
            "output": "not visible"
        },
        {
            "idx": 926,
            "output": "not visible"
        },
        {
            "idx": 927,
            "output": "not visible"
        },
        {
            "idx": 928,
            "output": "not visible"
        },
        {
            "idx": 929,
            "output": "not visible"
        },
        {
            "idx": 930,
            "output": "not visible"
        },
        {
            "idx": 931,
            "output": "not visible"
        },
        {
            "idx": 932,
            "output": "visible"
        },
        {
            "idx": 933,
            "output": "not visible"
        },
        {
            "idx": 934,
            "output": "visible"
        },
        {
            "idx": 936,
            "output": "not visible"
        },
        {
            "idx": 937,
            "output": "not visible"
        },
        {
            "idx": 938,
            "output": "not visible"
        },
        {
            "idx": 939,
            "output": "not visible"
        },
        {
            "idx": 941,
            "output": "not visible"
        },
        {
            "idx": 942,
            "output": "not visible"
        },
        {
            "idx": 945,
            "output": "not visible"
        },
        {
            "idx": 947,
            "output": "visible"
        },
        {
            "idx": 949,
            "output": "not visible"
        },
        {
            "idx": 951,
            "output": "not visible"
        },
        {
            "idx": 952,
            "output": "not visible"
        },
        {
            "idx": 953,
            "output": "not visible"
        },
        {
            "idx": 956,
            "output": "not visible"
        },
        {
            "idx": 957,
            "output": "not visible"
        },
        {
            "idx": 958,
            "output": "not visible"
        },
        {
            "idx": 959,
            "output": "not visible"
        },
        {
            "idx": 960,
            "output": "not visible"
        },
        {
            "idx": 961,
            "output": "not visible"
        },
        {
            "idx": 962,
            "output": "not visible"
        },
        {
            "idx": 964,
            "output": "not visible"
        },
        {
            "idx": 965,
            "output": "not visible"
        },
        {
            "idx": 966,
            "output": "not visible"
        },
        {
            "idx": 969,
            "output": "not visible"
        },
        {
            "idx": 971,
            "output": "not visible"
        },
        {
            "idx": 972,
            "output": "not visible"
        },
        {
            "idx": 973,
            "output": "not visible"
        },
        {
            "idx": 974,
            "output": "not visible"
        },
        {
            "idx": 975,
            "output": "not visible"
        },
        {
            "idx": 976,
            "output": "not visible"
        },
        {
            "idx": 977,
            "output": "not visible"
        },
        {
            "idx": 978,
            "output": "visible"
        },
        {
            "idx": 979,
            "output": "visible"
        },
        {
            "idx": 982,
            "output": "not visible"
        },
        {
            "idx": 983,
            "output": "not visible"
        },
        {
            "idx": 984,
            "output": "visible"
        },
        {
            "idx": 986,
            "output": "not visible"
        },
        {
            "idx": 987,
            "output": "not visible"
        },
        {
            "idx": 988,
            "output": "not visible"
        },
        {
            "idx": 990,
            "output": "not visible"
        },
        {
            "idx": 992,
            "output": "not visible"
        },
        {
            "idx": 993,
            "output": "not visible"
        },
        {
            "idx": 995,
            "output": "not visible"
        },
        {
            "idx": 996,
            "output": "not visible"
        },
        {
            "idx": 997,
            "output": "not visible"
        },
        {
            "idx": 999,
            "output": "visible"
        },
        {
            "idx": 1000,
            "output": "not visible"
        },
        {
            "idx": 1002,
            "output": "not visible"
        },
        {
            "idx": 1003,
            "output": "not visible"
        },
        {
            "idx": 1004,
            "output": "not visible"
        },
        {
            "idx": 1005,
            "output": "not visible"
        },
        {
            "idx": 1006,
            "output": "not visible"
        },
        {
            "idx": 1007,
            "output": "not visible"
        },
        {
            "idx": 1008,
            "output": "not visible"
        },
        {
            "idx": 1010,
            "output": "not visible"
        },
        {
            "idx": 1012,
            "output": "not visible"
        },
        {
            "idx": 1014,
            "output": "not visible"
        },
        {
            "idx": 1015,
            "output": "not visible"
        },
        {
            "idx": 1017,
            "output": "not visible"
        },
        {
            "idx": 1019,
            "output": "not visible"
        },
        {
            "idx": 1020,
            "output": "not visible"
        },
        {
            "idx": 1021,
            "output": "not visible"
        },
        {
            "idx": 1022,
            "output": "not visible"
        },
        {
            "idx": 1024,
            "output": "not visible"
        },
        {
            "idx": 1028,
            "output": "not visible"
        },
        {
            "idx": 1029,
            "output": "not visible"
        },
        {
            "idx": 1030,
            "output": "not visible"
        },
        {
            "idx": 1037,
            "output": "not visible"
        },
        {
            "idx": 1038,
            "output": "not visible"
        },
        {
            "idx": 1039,
            "output": "not visible"
        },
        {
            "idx": 1044,
            "output": "not visible"
        }
    ],
    "no": [
        {
            "idx": 0,
            "output": "not visible"
        },
        {
            "idx": 2,
            "output": "not visible"
        },
        {
            "idx": 8,
            "output": "not visible"
        },
        {
            "idx": 12,
            "output": "not visible"
        },
        {
            "idx": 13,
            "output": "not visible"
        },
        {
            "idx": 15,
            "output": "not visible"
        },
        {
            "idx": 16,
            "output": "not visible"
        },
        {
            "idx": 20,
            "output": "not visible"
        },
        {
            "idx": 23,
            "output": "not visible"
        },
        {
            "idx": 29,
            "output": "not visible"
        },
        {
            "idx": 32,
            "output": "not visible"
        },
        {
            "idx": 33,
            "output": "not visible"
        },
        {
            "idx": 36,
            "output": "not visible"
        },
        {
            "idx": 40,
            "output": "not visible"
        },
        {
            "idx": 41,
            "output": "not visible"
        },
        {
            "idx": 45,
            "output": "not visible"
        },
        {
            "idx": 47,
            "output": "not visible"
        },
        {
            "idx": 65,
            "output": "not visible"
        },
        {
            "idx": 70,
            "output": "not visible"
        },
        {
            "idx": 71,
            "output": "not visible"
        },
        {
            "idx": 72,
            "output": "not visible"
        },
        {
            "idx": 73,
            "output": "visible"
        },
        {
            "idx": 74,
            "output": "not visible"
        },
        {
            "idx": 75,
            "output": "not visible"
        },
        {
            "idx": 76,
            "output": "not visible"
        },
        {
            "idx": 77,
            "output": "not visible"
        },
        {
            "idx": 79,
            "output": "not visible"
        },
        {
            "idx": 80,
            "output": "not visible"
        },
        {
            "idx": 82,
            "output": "not visible"
        },
        {
            "idx": 83,
            "output": "not visible"
        },
        {
            "idx": 88,
            "output": "not visible"
        },
        {
            "idx": 89,
            "output": "not visible"
        },
        {
            "idx": 90,
            "output": "not visible"
        },
        {
            "idx": 93,
            "output": "not visible"
        },
        {
            "idx": 94,
            "output": "not visible"
        },
        {
            "idx": 97,
            "output": "not visible"
        },
        {
            "idx": 99,
            "output": "not visible"
        },
        {
            "idx": 100,
            "output": "not visible"
        },
        {
            "idx": 103,
            "output": "not visible"
        },
        {
            "idx": 104,
            "output": "not visible"
        },
        {
            "idx": 105,
            "output": "not visible"
        },
        {
            "idx": 107,
            "output": "not visible"
        },
        {
            "idx": 108,
            "output": "not visible"
        },
        {
            "idx": 109,
            "output": "not visible"
        },
        {
            "idx": 112,
            "output": "not visible"
        },
        {
            "idx": 113,
            "output": "not visible"
        },
        {
            "idx": 116,
            "output": "not visible"
        },
        {
            "idx": 117,
            "output": "not visible"
        },
        {
            "idx": 118,
            "output": "not visible"
        },
        {
            "idx": 120,
            "output": "visible"
        },
        {
            "idx": 121,
            "output": "not visible"
        },
        {
            "idx": 122,
            "output": "not visible"
        },
        {
            "idx": 123,
            "output": "not visible"
        },
        {
            "idx": 126,
            "output": "not visible"
        },
        {
            "idx": 127,
            "output": "not visible"
        },
        {
            "idx": 128,
            "output": "not visible"
        },
        {
            "idx": 132,
            "output": "not visible"
        },
        {
            "idx": 133,
            "output": "not visible"
        },
        {
            "idx": 138,
            "output": "not visible"
        },
        {
            "idx": 142,
            "output": "not visible"
        },
        {
            "idx": 143,
            "output": "not visible"
        },
        {
            "idx": 144,
            "output": "not visible"
        },
        {
            "idx": 145,
            "output": "not visible"
        },
        {
            "idx": 146,
            "output": "not visible"
        },
        {
            "idx": 147,
            "output": "not visible"
        },
        {
            "idx": 148,
            "output": "not visible"
        },
        {
            "idx": 149,
            "output": "not visible"
        },
        {
            "idx": 151,
            "output": "not visible"
        },
        {
            "idx": 153,
            "output": "not visible"
        },
        {
            "idx": 154,
            "output": "not visible"
        },
        {
            "idx": 155,
            "output": "not visible"
        },
        {
            "idx": 159,
            "output": "not visible"
        },
        {
            "idx": 160,
            "output": "not visible"
        },
        {
            "idx": 161,
            "output": "not visible"
        },
        {
            "idx": 163,
            "output": "not visible"
        },
        {
            "idx": 165,
            "output": "not visible"
        },
        {
            "idx": 168,
            "output": "not visible"
        },
        {
            "idx": 169,
            "output": "not visible"
        },
        {
            "idx": 172,
            "output": "not visible"
        },
        {
            "idx": 173,
            "output": "not visible"
        },
        {
            "idx": 175,
            "output": "not visible"
        },
        {
            "idx": 177,
            "output": "not visible"
        },
        {
            "idx": 178,
            "output": "not visible"
        },
        {
            "idx": 181,
            "output": "not visible"
        },
        {
            "idx": 182,
            "output": "visible"
        },
        {
            "idx": 184,
            "output": "not visible"
        },
        {
            "idx": 188,
            "output": "not visible"
        },
        {
            "idx": 189,
            "output": "not visible"
        },
        {
            "idx": 191,
            "output": "not visible"
        },
        {
            "idx": 194,
            "output": "not visible"
        },
        {
            "idx": 195,
            "output": "not visible"
        },
        {
            "idx": 197,
            "output": "not visible"
        },
        {
            "idx": 200,
            "output": "not visible"
        },
        {
            "idx": 201,
            "output": "not visible"
        },
        {
            "idx": 202,
            "output": "not visible"
        },
        {
            "idx": 203,
            "output": "not visible"
        },
        {
            "idx": 206,
            "output": "not visible"
        },
        {
            "idx": 208,
            "output": "not visible"
        },
        {
            "idx": 213,
            "output": "not visible"
        },
        {
            "idx": 214,
            "output": "not visible"
        },
        {
            "idx": 219,
            "output": "not visible"
        },
        {
            "idx": 221,
            "output": "not visible"
        },
        {
            "idx": 224,
            "output": "not visible"
        },
        {
            "idx": 225,
            "output": "not visible"
        },
        {
            "idx": 229,
            "output": "not visible"
        },
        {
            "idx": 234,
            "output": "not visible"
        },
        {
            "idx": 235,
            "output": "not visible"
        },
        {
            "idx": 236,
            "output": "not visible"
        },
        {
            "idx": 237,
            "output": "not visible"
        },
        {
            "idx": 238,
            "output": "not visible"
        },
        {
            "idx": 239,
            "output": "not visible"
        },
        {
            "idx": 240,
            "output": "not visible"
        },
        {
            "idx": 241,
            "output": "not visible"
        },
        {
            "idx": 242,
            "output": "not visible"
        },
        {
            "idx": 243,
            "output": "visible"
        },
        {
            "idx": 244,
            "output": "not visible"
        },
        {
            "idx": 245,
            "output": "not visible"
        },
        {
            "idx": 246,
            "output": "not visible"
        },
        {
            "idx": 248,
            "output": "not visible"
        },
        {
            "idx": 249,
            "output": "not visible"
        },
        {
            "idx": 250,
            "output": "not visible"
        },
        {
            "idx": 251,
            "output": "not visible"
        },
        {
            "idx": 253,
            "output": "not visible"
        },
        {
            "idx": 254,
            "output": "not visible"
        },
        {
            "idx": 255,
            "output": "not visible"
        },
        {
            "idx": 256,
            "output": "not visible"
        },
        {
            "idx": 257,
            "output": "not visible"
        },
        {
            "idx": 259,
            "output": "not visible"
        },
        {
            "idx": 260,
            "output": "not visible"
        },
        {
            "idx": 261,
            "output": "not visible"
        },
        {
            "idx": 264,
            "output": "not visible"
        },
        {
            "idx": 265,
            "output": "not visible"
        },
        {
            "idx": 267,
            "output": "not visible"
        },
        {
            "idx": 268,
            "output": "not visible"
        },
        {
            "idx": 269,
            "output": "not visible"
        },
        {
            "idx": 270,
            "output": "not visible"
        },
        {
            "idx": 271,
            "output": "not visible"
        },
        {
            "idx": 272,
            "output": "not visible"
        },
        {
            "idx": 274,
            "output": "not visible"
        },
        {
            "idx": 275,
            "output": "not visible"
        },
        {
            "idx": 279,
            "output": "not visible"
        },
        {
            "idx": 282,
            "output": "not visible"
        },
        {
            "idx": 283,
            "output": "not visible"
        },
        {
            "idx": 287,
            "output": "not visible"
        },
        {
            "idx": 290,
            "output": "not visible"
        },
        {
            "idx": 294,
            "output": "not visible"
        },
        {
            "idx": 295,
            "output": "not visible"
        },
        {
            "idx": 296,
            "output": "not visible"
        },
        {
            "idx": 303,
            "output": "not visible"
        },
        {
            "idx": 304,
            "output": "not visible"
        },
        {
            "idx": 306,
            "output": "not visible"
        },
        {
            "idx": 308,
            "output": "not visible"
        },
        {
            "idx": 314,
            "output": "not visible"
        },
        {
            "idx": 323,
            "output": "not visible"
        },
        {
            "idx": 327,
            "output": "not visible"
        },
        {
            "idx": 330,
            "output": "not visible"
        },
        {
            "idx": 334,
            "output": "not visible"
        },
        {
            "idx": 338,
            "output": "not visible"
        },
        {
            "idx": 341,
            "output": "not visible"
        },
        {
            "idx": 343,
            "output": "not visible"
        },
        {
            "idx": 345,
            "output": "not visible"
        },
        {
            "idx": 347,
            "output": "not visible"
        },
        {
            "idx": 353,
            "output": "not visible"
        },
        {
            "idx": 354,
            "output": "not visible"
        },
        {
            "idx": 356,
            "output": "not visible"
        },
        {
            "idx": 357,
            "output": "not visible"
        },
        {
            "idx": 358,
            "output": "not visible"
        },
        {
            "idx": 362,
            "output": "not visible"
        },
        {
            "idx": 364,
            "output": "not visible"
        },
        {
            "idx": 366,
            "output": "not visible"
        },
        {
            "idx": 369,
            "output": "not visible"
        },
        {
            "idx": 370,
            "output": "not visible"
        },
        {
            "idx": 377,
            "output": "not visible"
        },
        {
            "idx": 379,
            "output": "not visible"
        },
        {
            "idx": 396,
            "output": "not visible"
        },
        {
            "idx": 398,
            "output": "not visible"
        },
        {
            "idx": 406,
            "output": "not visible"
        },
        {
            "idx": 409,
            "output": "not visible"
        },
        {
            "idx": 414,
            "output": "not visible"
        },
        {
            "idx": 420,
            "output": "not visible"
        },
        {
            "idx": 421,
            "output": "not visible"
        },
        {
            "idx": 423,
            "output": "not visible"
        },
        {
            "idx": 425,
            "output": "not visible"
        },
        {
            "idx": 426,
            "output": "not visible"
        },
        {
            "idx": 432,
            "output": "not visible"
        },
        {
            "idx": 437,
            "output": "not visible"
        },
        {
            "idx": 439,
            "output": "not visible"
        },
        {
            "idx": 441,
            "output": "not visible"
        },
        {
            "idx": 444,
            "output": "not visible"
        },
        {
            "idx": 445,
            "output": "not visible"
        },
        {
            "idx": 450,
            "output": "not visible"
        },
        {
            "idx": 457,
            "output": "not visible"
        },
        {
            "idx": 467,
            "output": "not visible"
        },
        {
            "idx": 469,
            "output": "not visible"
        },
        {
            "idx": 471,
            "output": "not visible"
        },
        {
            "idx": 475,
            "output": "not visible"
        },
        {
            "idx": 476,
            "output": "not visible"
        },
        {
            "idx": 480,
            "output": "not visible"
        },
        {
            "idx": 481,
            "output": "not visible"
        },
        {
            "idx": 482,
            "output": "not visible"
        },
        {
            "idx": 491,
            "output": "not visible"
        },
        {
            "idx": 492,
            "output": "not visible"
        },
        {
            "idx": 493,
            "output": "not visible"
        },
        {
            "idx": 494,
            "output": "not visible"
        },
        {
            "idx": 496,
            "output": "not visible"
        },
        {
            "idx": 499,
            "output": "not visible"
        },
        {
            "idx": 502,
            "output": "not visible"
        },
        {
            "idx": 503,
            "output": "not visible"
        },
        {
            "idx": 506,
            "output": "visible"
        },
        {
            "idx": 507,
            "output": "visible"
        },
        {
            "idx": 514,
            "output": "not visible"
        },
        {
            "idx": 516,
            "output": "not visible"
        },
        {
            "idx": 517,
            "output": "not visible"
        },
        {
            "idx": 526,
            "output": "visible"
        },
        {
            "idx": 536,
            "output": "not visible"
        },
        {
            "idx": 538,
            "output": "not visible"
        },
        {
            "idx": 545,
            "output": "not visible"
        },
        {
            "idx": 547,
            "output": "not visible"
        },
        {
            "idx": 554,
            "output": "not visible"
        },
        {
            "idx": 558,
            "output": "visible"
        },
        {
            "idx": 560,
            "output": "not visible"
        },
        {
            "idx": 569,
            "output": "not visible"
        },
        {
            "idx": 572,
            "output": "not visible"
        },
        {
            "idx": 576,
            "output": "not visible"
        },
        {
            "idx": 579,
            "output": "not visible"
        },
        {
            "idx": 580,
            "output": "not visible"
        },
        {
            "idx": 581,
            "output": "not visible"
        },
        {
            "idx": 583,
            "output": "not visible"
        },
        {
            "idx": 586,
            "output": "not visible"
        },
        {
            "idx": 588,
            "output": "not visible"
        },
        {
            "idx": 590,
            "output": "not visible"
        },
        {
            "idx": 594,
            "output": "not visible"
        },
        {
            "idx": 595,
            "output": "not visible"
        },
        {
            "idx": 596,
            "output": "not visible"
        },
        {
            "idx": 599,
            "output": "not visible"
        },
        {
            "idx": 601,
            "output": "not visible"
        },
        {
            "idx": 607,
            "output": "not visible"
        },
        {
            "idx": 614,
            "output": "not visible"
        },
        {
            "idx": 620,
            "output": "not visible"
        },
        {
            "idx": 621,
            "output": "not visible"
        },
        {
            "idx": 628,
            "output": "not visible"
        },
        {
            "idx": 629,
            "output": "not visible"
        },
        {
            "idx": 634,
            "output": "not visible"
        },
        {
            "idx": 638,
            "output": "not visible"
        },
        {
            "idx": 639,
            "output": "not visible"
        },
        {
            "idx": 640,
            "output": "not visible"
        },
        {
            "idx": 643,
            "output": "not visible"
        },
        {
            "idx": 644,
            "output": "not visible"
        },
        {
            "idx": 645,
            "output": "not visible"
        },
        {
            "idx": 646,
            "output": "not visible"
        },
        {
            "idx": 648,
            "output": "not visible"
        },
        {
            "idx": 649,
            "output": "not visible"
        },
        {
            "idx": 650,
            "output": "not visible"
        },
        {
            "idx": 651,
            "output": "not visible"
        },
        {
            "idx": 654,
            "output": "not visible"
        },
        {
            "idx": 655,
            "output": "not visible"
        },
        {
            "idx": 657,
            "output": "not visible"
        },
        {
            "idx": 659,
            "output": "not visible"
        },
        {
            "idx": 660,
            "output": "not visible"
        },
        {
            "idx": 662,
            "output": "not visible"
        },
        {
            "idx": 665,
            "output": "not visible"
        },
        {
            "idx": 669,
            "output": "not visible"
        },
        {
            "idx": 673,
            "output": "not visible"
        },
        {
            "idx": 678,
            "output": "not visible"
        },
        {
            "idx": 681,
            "output": "not visible"
        },
        {
            "idx": 688,
            "output": "not visible"
        },
        {
            "idx": 692,
            "output": "visible"
        },
        {
            "idx": 697,
            "output": "not visible"
        },
        {
            "idx": 699,
            "output": "not visible"
        },
        {
            "idx": 700,
            "output": "not visible"
        },
        {
            "idx": 701,
            "output": "not visible"
        },
        {
            "idx": 708,
            "output": "not visible"
        },
        {
            "idx": 710,
            "output": "not visible"
        },
        {
            "idx": 711,
            "output": "not visible"
        },
        {
            "idx": 713,
            "output": "not visible"
        },
        {
            "idx": 721,
            "output": "not visible"
        },
        {
            "idx": 724,
            "output": "not visible"
        },
        {
            "idx": 728,
            "output": "not visible"
        },
        {
            "idx": 730,
            "output": "not visible"
        },
        {
            "idx": 736,
            "output": "not visible"
        },
        {
            "idx": 743,
            "output": "not visible"
        },
        {
            "idx": 744,
            "output": "not visible"
        },
        {
            "idx": 752,
            "output": "not visible"
        },
        {
            "idx": 754,
            "output": "not visible"
        },
        {
            "idx": 755,
            "output": "not visible"
        },
        {
            "idx": 758,
            "output": "not visible"
        },
        {
            "idx": 761,
            "output": "not visible"
        },
        {
            "idx": 762,
            "output": "not visible"
        },
        {
            "idx": 763,
            "output": "not visible"
        },
        {
            "idx": 767,
            "output": "not visible"
        },
        {
            "idx": 768,
            "output": "not visible"
        },
        {
            "idx": 772,
            "output": "not visible"
        },
        {
            "idx": 773,
            "output": "not visible"
        },
        {
            "idx": 779,
            "output": "not visible"
        },
        {
            "idx": 783,
            "output": "not visible"
        },
        {
            "idx": 784,
            "output": "not visible"
        },
        {
            "idx": 789,
            "output": "not visible"
        },
        {
            "idx": 795,
            "output": "not visible"
        },
        {
            "idx": 799,
            "output": "not visible"
        },
        {
            "idx": 805,
            "output": "not visible"
        },
        {
            "idx": 815,
            "output": "not visible"
        },
        {
            "idx": 822,
            "output": "not visible"
        },
        {
            "idx": 833,
            "output": "visible"
        },
        {
            "idx": 834,
            "output": "visible"
        },
        {
            "idx": 836,
            "output": "not visible"
        },
        {
            "idx": 840,
            "output": "not visible"
        },
        {
            "idx": 842,
            "output": "not visible"
        },
        {
            "idx": 850,
            "output": "not visible"
        },
        {
            "idx": 852,
            "output": "not visible"
        },
        {
            "idx": 853,
            "output": "not visible"
        },
        {
            "idx": 855,
            "output": "not visible"
        },
        {
            "idx": 856,
            "output": "not visible"
        },
        {
            "idx": 857,
            "output": "visible"
        },
        {
            "idx": 864,
            "output": "not visible"
        },
        {
            "idx": 870,
            "output": "not visible"
        },
        {
            "idx": 873,
            "output": "not visible"
        },
        {
            "idx": 874,
            "output": "not visible"
        },
        {
            "idx": 875,
            "output": "not visible"
        },
        {
            "idx": 877,
            "output": "not visible"
        },
        {
            "idx": 878,
            "output": "not visible"
        },
        {
            "idx": 881,
            "output": "not visible"
        },
        {
            "idx": 882,
            "output": "not visible"
        },
        {
            "idx": 884,
            "output": "not visible"
        },
        {
            "idx": 885,
            "output": "not visible"
        },
        {
            "idx": 887,
            "output": "not visible"
        },
        {
            "idx": 889,
            "output": "not visible"
        },
        {
            "idx": 890,
            "output": "not visible"
        },
        {
            "idx": 895,
            "output": "not visible"
        },
        {
            "idx": 898,
            "output": "not visible"
        },
        {
            "idx": 911,
            "output": "not visible"
        },
        {
            "idx": 914,
            "output": "not visible"
        },
        {
            "idx": 917,
            "output": "not visible"
        },
        {
            "idx": 918,
            "output": "not visible"
        },
        {
            "idx": 922,
            "output": "not visible"
        },
        {
            "idx": 925,
            "output": "not visible"
        },
        {
            "idx": 935,
            "output": "not visible"
        },
        {
            "idx": 940,
            "output": "visible"
        },
        {
            "idx": 943,
            "output": "not visible"
        },
        {
            "idx": 944,
            "output": "not visible"
        },
        {
            "idx": 946,
            "output": "not visible"
        },
        {
            "idx": 948,
            "output": "not visible"
        },
        {
            "idx": 950,
            "output": "not visible"
        },
        {
            "idx": 954,
            "output": "not visible"
        },
        {
            "idx": 955,
            "output": "not visible"
        },
        {
            "idx": 963,
            "output": "not visible"
        },
        {
            "idx": 967,
            "output": "not visible"
        },
        {
            "idx": 968,
            "output": "not visible"
        },
        {
            "idx": 970,
            "output": "not visible"
        },
        {
            "idx": 980,
            "output": "not visible"
        },
        {
            "idx": 981,
            "output": "not visible"
        },
        {
            "idx": 985,
            "output": "not visible"
        },
        {
            "idx": 989,
            "output": "not visible"
        },
        {
            "idx": 991,
            "output": "not visible"
        },
        {
            "idx": 994,
            "output": "not visible"
        },
        {
            "idx": 998,
            "output": "not visible"
        },
        {
            "idx": 1001,
            "output": "not visible"
        },
        {
            "idx": 1009,
            "output": "not visible"
        },
        {
            "idx": 1011,
            "output": "not visible"
        },
        {
            "idx": 1013,
            "output": "not visible"
        },
        {
            "idx": 1016,
            "output": "not visible"
        },
        {
            "idx": 1018,
            "output": "not visible"
        },
        {
            "idx": 1023,
            "output": "not visible"
        },
        {
            "idx": 1025,
            "output": "not visible"
        },
        {
            "idx": 1026,
            "output": "not visible"
        },
        {
            "idx": 1027,
            "output": "not visible"
        },
        {
            "idx": 1031,
            "output": "not visible"
        },
        {
            "idx": 1032,
            "output": "not visible"
        },
        {
            "idx": 1033,
            "output": "not visible"
        },
        {
            "idx": 1034,
            "output": "not visible"
        },
        {
            "idx": 1035,
            "output": "not visible"
        },
        {
            "idx": 1036,
            "output": "not visible"
        },
        {
            "idx": 1040,
            "output": "not visible"
        },
        {
            "idx": 1041,
            "output": "not visible"
        },
        {
            "idx": 1042,
            "output": "not visible"
        },
        {
            "idx": 1043,
            "output": "not visible"
        }
    ]
}